{"nodes": [{"id": "services_cost_service_src_models_cost_rs", "label": "cost.rs", "file_type": "code", "source_file": "services/cost-service/src/models/cost.rs", "source_location": "L1"}, {"id": "cost_costoverview", "label": "CostOverview", "file_type": "code", "source_file": "services/cost-service/src/models/cost.rs", "source_location": "L7"}, {"id": "cost_servicecost", "label": "ServiceCost", "file_type": "code", "source_file": "services/cost-service/src/models/cost.rs", "source_location": "L16"}, {"id": "cost_dailycost", "label": "DailyCost", "file_type": "code", "source_file": "services/cost-service/src/models/cost.rs", "source_location": "L24"}, {"id": "cost_budget", "label": "Budget", "file_type": "code", "source_file": "services/cost-service/src/models/cost.rs", "source_location": "L30"}, {"id": "cost_budgetperiod", "label": "BudgetPeriod", "file_type": "code", "source_file": "services/cost-service/src/models/cost.rs", "source_location": "L41"}, {"id": "cost_createbudgetrequest", "label": "CreateBudgetRequest", "file_type": "code", "source_file": "services/cost-service/src/models/cost.rs", "source_location": "L48"}, {"id": "cost_costrecommendation", "label": "CostRecommendation", "file_type": "code", "source_file": "services/cost-service/src/models/cost.rs", "source_location": "L56"}, {"id": "cost_recommendationcategory", "label": "RecommendationCategory", "file_type": "code", "source_file": "services/cost-service/src/models/cost.rs", "source_location": "L68"}, {"id": "cost_effortlevel", "label": "EffortLevel", "file_type": "code", "source_file": "services/cost-service/src/models/cost.rs", "source_location": "L77"}, {"id": "cost_costforecast", "label": "CostForecast", "file_type": "code", "source_file": "services/cost-service/src/models/cost.rs", "source_location": "L84"}, {"id": "cost_reservation", "label": "Reservation", "file_type": "code", "source_file": "services/cost-service/src/models/cost.rs", "source_location": "L92"}, {"id": "cost_wastedresource", "label": "WastedResource", "file_type": "code", "source_file": "services/cost-service/src/models/cost.rs", "source_location": "L105"}, {"id": "cost_costexplorerquery", "label": "CostExplorerQuery", "file_type": "code", "source_file": "services/cost-service/src/models/cost.rs", "source_location": "L117"}], "edges": [{"source": "services_cost_service_src_models_cost_rs", "target": "naivedate", "relation": "imports_from", "confidence": "EXTRACTED", "source_file": "services/cost-service/src/models/cost.rs", "source_location": "L1", "weight": 1.0}, {"source": "services_cost_service_src_models_cost_rs", "target": "serde", "relation": "imports_from", "confidence": "EXTRACTED", "source_file": "services/cost-service/src/models/cost.rs", "source_location": "L2", "weight": 1.0}, {"source": "services_cost_service_src_models_cost_rs", "target": "hashmap", "relation": "imports_from", "confidence": "EXTRACTED", "source_file": "services/cost-service/src/models/cost.rs", "source_location": "L3", "weight": 1.0}, {"source": "services_cost_service_src_models_cost_rs", "target": "uuid", "relation": "imports_from", "confidence": "EXTRACTED", "source_file": "services/cost-service/src/models/cost.rs", "source_location": "L4", "weight": 1.0}, {"source": "services_cost_service_src_models_cost_rs", "target": "cost_costoverview", "relation": "contains", "confidence": "EXTRACTED", "source_file": "services/cost-service/src/models/cost.rs", "source_location": "L7", "weight": 1.0}, {"source": "services_cost_service_src_models_cost_rs", "target": "cost_servicecost", "relation": "contains", "confidence": "EXTRACTED", "source_file": "services/cost-service/src/models/cost.rs", "source_location": "L16", "weight": 1.0}, {"source": "services_cost_service_src_models_cost_rs", "target": "cost_dailycost", "relation": "contains", "confidence": "EXTRACTED", "source_file": "services/cost-service/src/models/cost.rs", "source_location": "L24", "weight": 1.0}, {"source": "services_cost_service_src_models_cost_rs", "target": "cost_budget", "relation": "contains", "confidence": "EXTRACTED", "source_file": "services/cost-service/src/models/cost.rs", "source_location": "L30", "weight": 1.0}, {"source": "services_cost_service_src_models_cost_rs", "target": "cost_budgetperiod", "relation": "contains", "confidence": "EXTRACTED", "source_file": "services/cost-service/src/models/cost.rs", "source_location": "L41", "weight": 1.0}, {"source": "services_cost_service_src_models_cost_rs", "target": "cost_createbudgetrequest", "relation": "contains", "confidence": "EXTRACTED", "source_file": "services/cost-service/src/models/cost.rs", "source_location": "L48", "weight": 1.0}, {"source": "services_cost_service_src_models_cost_rs", "target": "cost_costrecommendation", "relation": "contains", "confidence": "EXTRACTED", "source_file": "services/cost-service/src/models/cost.rs", "source_location": "L56", "weight": 1.0}, {"source": "services_cost_service_src_models_cost_rs", "target": "cost_recommendationcategory", "relation": "contains", "confidence": "EXTRACTED", "source_file": "services/cost-service/src/models/cost.rs", "source_location": "L68", "weight": 1.0}, {"source": "services_cost_service_src_models_cost_rs", "target": "cost_effortlevel", "relation": "contains", "confidence": "EXTRACTED", "source_file": "services/cost-service/src/models/cost.rs", "source_location": "L77", "weight": 1.0}, {"source": "services_cost_service_src_models_cost_rs", "target": "cost_costforecast", "relation": "contains", "confidence": "EXTRACTED", "source_file": "services/cost-service/src/models/cost.rs", "source_location": "L84", "weight": 1.0}, {"source": "services_cost_service_src_models_cost_rs", "target": "cost_reservation", "relation": "contains", "confidence": "EXTRACTED", "source_file": "services/cost-service/src/models/cost.rs", "source_location": "L92", "weight": 1.0}, {"source": "services_cost_service_src_models_cost_rs", "target": "cost_wastedresource", "relation": "contains", "confidence": "EXTRACTED", "source_file": "services/cost-service/src/models/cost.rs", "source_location": "L105", "weight": 1.0}, {"source": "services_cost_service_src_models_cost_rs", "target": "cost_costexplorerquery", "relation": "contains", "confidence": "EXTRACTED", "source_file": "services/cost-service/src/models/cost.rs", "source_location": "L117", "weight": 1.0}], "raw_calls": []}