{"nodes": [{"id": "compliance_code_generateterraform", "label": "generate_terraform", "file_type": "code", "source_file": "services/security-service/src/handlers/compliance_code.rs", "source_location": null, "source_url": null, "captured_at": null, "author": null, "contributor": null}, {"id": "compliance_code_generateopa", "label": "generate_opa", "file_type": "code", "source_file": "services/security-service/src/handlers/compliance_code.rs", "source_location": null, "source_url": null, "captured_at": null, "author": null, "contributor": null}], "edges": [{"source": "compliance_code_generateterraform", "target": "compliance_complianceframework", "relation": "references", "confidence": "EXTRACTED", "confidence_score": 1.0, "source_file": "services/security-service/src/handlers/compliance_code.rs", "source_location": null, "weight": 1.0}, {"source": "compliance_code_generateopa", "target": "compliance_complianceframework", "relation": "references", "confidence": "EXTRACTED", "confidence_score": 1.0, "source_file": "services/security-service/src/handlers/compliance_code.rs", "source_location": null, "weight": 1.0}], "hyperedges": []}