{"nodes": [{"id": "apps_web_hooks_use_analytics_ts", "label": "use-analytics.ts", "file_type": "code", "source_file": "apps/web/hooks/use-analytics.ts", "source_location": "L1"}, {"id": "use_analytics_useanalyticsquery", "label": "useAnalyticsQuery()", "file_type": "code", "source_file": "apps/web/hooks/use-analytics.ts", "source_location": "L32"}, {"id": "use_analytics_usevisualizations", "label": "useVisualizations()", "file_type": "code", "source_file": "apps/web/hooks/use-analytics.ts", "source_location": "L44"}, {"id": "use_analytics_usereports", "label": "useReports()", "file_type": "code", "source_file": "apps/web/hooks/use-analytics.ts", "source_location": "L52"}, {"id": "use_analytics_usesearchindexes", "label": "useSearchIndexes()", "file_type": "code", "source_file": "apps/web/hooks/use-analytics.ts", "source_location": "L78"}, {"id": "use_analytics_usesearchresults", "label": "useSearchResults()", "file_type": "code", "source_file": "apps/web/hooks/use-analytics.ts", "source_location": "L86"}], "edges": [{"source": "apps_web_hooks_use_analytics_ts", "target": "react_query", "relation": "imports_from", "confidence": "EXTRACTED", "source_file": "apps/web/hooks/use-analytics.ts", "source_location": "L1", "weight": 1.0}, {"source": "apps_web_hooks_use_analytics_ts", "target": "api_client", "relation": "imports_from", "confidence": "EXTRACTED", "source_file": "apps/web/hooks/use-analytics.ts", "source_location": "L2", "weight": 1.0}, {"source": "apps_web_hooks_use_analytics_ts", "target": "use_analytics_useanalyticsquery", "relation": "contains", "confidence": "EXTRACTED", "source_file": "apps/web/hooks/use-analytics.ts", "source_location": "L32", "weight": 1.0}, {"source": "apps_web_hooks_use_analytics_ts", "target": "use_analytics_usevisualizations", "relation": "contains", "confidence": "EXTRACTED", "source_file": "apps/web/hooks/use-analytics.ts", "source_location": "L44", "weight": 1.0}, {"source": "apps_web_hooks_use_analytics_ts", "target": "use_analytics_usereports", "relation": "contains", "confidence": "EXTRACTED", "source_file": "apps/web/hooks/use-analytics.ts", "source_location": "L52", "weight": 1.0}, {"source": "apps_web_hooks_use_analytics_ts", "target": "use_analytics_usesearchindexes", "relation": "contains", "confidence": "EXTRACTED", "source_file": "apps/web/hooks/use-analytics.ts", "source_location": "L78", "weight": 1.0}, {"source": "apps_web_hooks_use_analytics_ts", "target": "use_analytics_usesearchresults", "relation": "contains", "confidence": "EXTRACTED", "source_file": "apps/web/hooks/use-analytics.ts", "source_location": "L86", "weight": 1.0}], "raw_calls": [{"caller_nid": "use_analytics_useanalyticsquery", "callee": "useQuery", "source_file": "apps/web/hooks/use-analytics.ts", "source_location": "L36"}, {"caller_nid": "use_analytics_usevisualizations", "callee": "useQuery", "source_file": "apps/web/hooks/use-analytics.ts", "source_location": "L45"}, {"caller_nid": "use_analytics_usereports", "callee": "useQuery", "source_file": "apps/web/hooks/use-analytics.ts", "source_location": "L53"}, {"caller_nid": "use_analytics_usesearchindexes", "callee": "useQuery", "source_file": "apps/web/hooks/use-analytics.ts", "source_location": "L79"}, {"caller_nid": "use_analytics_usesearchresults", "callee": "useQuery", "source_file": "apps/web/hooks/use-analytics.ts", "source_location": "L87"}]}